README.rst
setup.py
fcc/__init__.py
fcc/census_block_conversions.py
fcc/core.py
fcc.egg-info/PKG-INFO
fcc.egg-info/SOURCES.txt
fcc.egg-info/dependency_links.txt
fcc.egg-info/entry_points.txt
fcc.egg-info/requires.txt
fcc.egg-info/top_level.txt