Metadata-Version: 1.1
Name: fcc
Version: 0.1.3
Summary: Python interface for Federal Communication Commission web API
Home-page: http://github.com/selik/fcc-api/
Author: Michael Selik
Author-email: mike@selik.org
License: MIT
Platform: any
Classifier: Development Status :: 3 - Alpha
Classifier: Intended Audience :: Developers
Classifier: License :: OSI Approved :: MIT License
Classifier: Natural Language :: English
Classifier: Operating System :: OS Independent
Classifier: Programming Language :: Python
